LICENSE
README.md
pyproject.toml
setup.py
cpp/smiles_fp.cpp
smiles_fp/__init__.py
smiles_fp/_smiles_fp.pyi
smiles_fp/search.py
smiles_fp.egg-info/PKG-INFO
smiles_fp.egg-info/SOURCES.txt
smiles_fp.egg-info/dependency_links.txt
smiles_fp.egg-info/requires.txt
smiles_fp.egg-info/top_level.txt
tests/test_smiles_fp.py