Metadata-Version: 2.4
Name: smiles-fp
Version: 0.1.2025.3.6
Summary: Multithreaded Tanimoto Similarity for RDKit Fingerprints.
Requires-Python: <3.14,>=3.10
License-File: LICENSE
Requires-Dist: numpy<2.0
Requires-Dist: rdkit==2025.03.6
Provides-Extra: dev
Requires-Dist: joblib; extra == "dev"
Requires-Dist: tqdm; extra == "dev"
Requires-Dist: pytest; extra == "dev"
Requires-Dist: pytest-benchmark; extra == "dev"
Dynamic: license-file
